MANIFEST.in
README.rst
setup.py
aliyun_python_sdk_ivpd.egg-info/PKG-INFO
aliyun_python_sdk_ivpd.egg-info/SOURCES.txt
aliyun_python_sdk_ivpd.egg-info/dependency_links.txt
aliyun_python_sdk_ivpd.egg-info/requires.txt
aliyun_python_sdk_ivpd.egg-info/top_level.txt
aliyunsdkivpd/__init__.py
aliyunsdkivpd/endpoint.py
aliyunsdkivpd/request/__init__.py
aliyunsdkivpd/request/v20190625/ChangeImageSizeRequest.py
aliyunsdkivpd/request/v20190625/CreateSegmentBodyJobRequest.py
aliyunsdkivpd/request/v20190625/DetectImageElementsRequest.py
aliyunsdkivpd/request/v20190625/EraseLogoInVideoRequest.py
aliyunsdkivpd/request/v20190625/ExtendImageStyleRequest.py
aliyunsdkivpd/request/v20190625/GetAsyncJobResultRequest.py
aliyunsdkivpd/request/v20190625/GetAsyncResultRequest.py
aliyunsdkivpd/request/v20190625/GetJobResultRequest.py
aliyunsdkivpd/request/v20190625/GetJobStatusRequest.py
aliyunsdkivpd/request/v20190625/GetRenderResultRequest.py
aliyunsdkivpd/request/v20190625/GetUserBucketConfigRequest.py
aliyunsdkivpd/request/v20190625/HighlightGameVideoRequest.py
aliyunsdkivpd/request/v20190625/ListPackageDesignModelTypesRequest.py
aliyunsdkivpd/request/v20190625/ListUserBucketsRequest.py
aliyunsdkivpd/request/v20190625/MakeSuperResolutionImageRequest.py
aliyunsdkivpd/request/v20190625/PreviewModelForPackageDesignRequest.py
aliyunsdkivpd/request/v20190625/RecognizeImageColorRequest.py
aliyunsdkivpd/request/v20190625/RecognizeImageStyleRequest.py
aliyunsdkivpd/request/v20190625/RecolorImageRequest.py
aliyunsdkivpd/request/v20190625/RenderImageForPackageDesignRequest.py
aliyunsdkivpd/request/v20190625/SegmentBodyRequest.py
aliyunsdkivpd/request/v20190625/SegmentImageRequest.py
aliyunsdkivpd/request/v20190625/UpdateUserBucketConfigRequest.py
aliyunsdkivpd/request/v20190625/__init__.py